<?xml version="1.0" encoding="UTF-8"?>
<MV2>
<Movie2>
<producttype2>DVD</producttype2>
<productname2>A Farewell To Arms</productname2>
<artistfirstname2>Ernest</artistfirstname2>
<artistlastname2>Hemingway</artistlastname2>
<artist2firstname2>Frank</artist2firstname2>
<artist2lastname2>Borzage</artist2lastname2>
<description2>Film adaptation of the classic novel. The tragic tale of love and loss during WWI.</description2>
<company2>20th Century Fox</company2>
<year2>1957</year2>
<productid2>B0007PALN4</productid2>
<price2>12.99</price2>
</Movie2>
<Movie2>
<producttype2>DVD</producttype2>
<productname2>A Tale of Two Cities</productname2>
<artistfirstname2>Charles</artistfirstname2>
<artistlastname2>Dickens</artistlastname2>
<artist2firstname2>Jack</artist2firstname2>
<artist2lastname2>Conway</artist2lastname2>
<description2>Film adaptation of the classic novel. Classic telling of life in two cities, London and Paris, during the upheaval of the French Revolution.</description2>
<company2>Warner Bros</company2>
<year2>1935</year2>
<productid2>B000GRUQL0</productid2>
<price2>17.49</price2>
</Movie2>
<Movie2>
<producttype2>DVD</producttype2>
<productname2>Adventures of Huckleberry Finn</productname2>
<artistfirstname2>Mark</artistfirstname2>
<artistlastname2>Twain</artistlastname2>
<artist2firstname2>Stephen</artist2firstname2>
<artist2lastname2>Sommers</artist2lastname2>
<description2>Film adaptation of the classic novel. Classic American story of adventure and self-discovery in pre-Civil War Missouri.</description2>
<company2>Walt Disney Video</company2>
<year2>2002</year2>
<productid2>B00005TPMM</productid2>
<price2>11.99</price2>
</Movie2>
<Movie2>
<producttype2>DVD</producttype2>
<productname2>Anna Karenina</productname2>
<artistfirstname2>Leo</artistfirstname2>
<artistlastname2>Tolstoy</artistlastname2>
<artist2firstname2>Julien</artist2firstname2>
<artist2lastname2>Duvivier</artist2lastname2>
<description2>Film adaptation of the classic novel. Intricate intrigue of love and scandal in high society of Czarist Russia.</description2>
<company2>20th Century Fox</company2>
<year2>1948</year2>
<productid2>B000MGBLHI</productid2>
<price2>14.99</price2>
</Movie2>
<Movie2>
<image href="file://images/6301966465.jpg" />
<producttype2>VHS</producttype2>
<productname2>Cannery Row</productname2>
<artistfirstname2>John</artistfirstname2>
<artistlastname2>Steinbeck</artistlastname2>
<description2>Film adaptation of the classic novel. A slice of blue collar life and love and laughter during the Great Depression Monterrey, California</description2>
<company2>MGM</company2>
<year2>1982</year2>
<productid2>6301966465</productid2>
<price2>25.99</price2>
</Movie2>
<Movie2>
<image href="file://images/B0000A5A1L.jpg" />
<producttype2>DVD</producttype2>
<productname2>Crime and Punishment</productname2>
<artistfirstname2>Fyodor</artistfirstname2>
<artistlastname2>Dostoyevsky</artistlastname2>
<artist2firstname2>Michael</artist2firstname2>
<artist2lastname2>Darlow</artist2lastname2>
<description2>Film adaptation of the classic novel. A tale of murder and justice in Czarist Russia</description2>
<company2>WEA</company2>
<year2>2003</year2>
<productid2>B0000A5A1L</productid2>
<price2>17.99</price2>
</Movie2>
<Movie2>
<producttype2>DVD</producttype2>
<productname2>David Copperfield</productname2>
<artistfirstname2>Charles</artistfirstname2>
<artistlastname2>Dickens</artistlastname2>
<artist2firstname2>George</artist2firstname2>
<artist2lastname2>Cukor</artist2lastname2>
<description2>Personal adventure of the title character in England in the early 1800s.</description2>
<company2>Warner Bros</company2>
<year2>1935</year2>
<productid2>B000GRUQK6</productid2>
<price2>17.99</price2>
</Movie2>
<Movie2>
<image href="file://images/B0000WN118.jpg" />
<producttype2>DVD</producttype2>
<productname2>Death in Venice</productname2>
<artistfirstname2>Thomas</artistfirstname2>
<artistlastname2>Mann</artistlastname2>
<description2>Film adaptation of the classic novel. Exploration of forbidden love and obsession with Venice in the background.</description2>
<company2>Warner Bros</company2>
<year2>1971</year2>
<productid2>B0000WN118</productid2>
<price2>17.99</price2>
</Movie2>
<Movie2>
<image href="file://images/6303560040.jpg" />
<producttype2>VHS</producttype2>
<productname2>For Whom the Bell Tolls</productname2>
<artistfirstname2>Ernest</artistfirstname2>
<artistlastname2>Hemingway</artistlastname2>
<artist2firstname2>Sam</artist2firstname2>
<artist2lastname2>Wood</artist2lastname2>
<description2>Film adaptation of the classic personal drama set in the Spanish Civil War.</description2>
<company2>Universal Studios</company2>
<year2>1943</year2>
<productid2>6303560040</productid2>
<price2>14.98</price2>
</Movie2>
<Movie2>
<producttype2>DVD</producttype2>
<productname2>Les Misérables</productname2>
<artistfirstname2>Victor</artistfirstname2>
<artistlastname2>Hugo</artistlastname2>
<artist2firstname2>Richard</artist2firstname2>
<artist2lastname2>Boleslawski</artist2lastname2>
<description2>Film adaptation of the classic novel. Rich tale of crime, sin, punishment and redemption in pre-revolutionary France.</description2>
<company2>20th Century Fox</company2>
<year2>1935</year2>
<productid2>B000MGBLI2</productid2>
<price2>9.95</price2>
</Movie2>
<Movie2>
<image href="file://images/6305081832.jpg" />
<producttype2>DVD</producttype2>
<productname2>Of Mice and Men</productname2>
<artistfirstname2>John</artistfirstname2>
<artistlastname2>Steinbeck</artistlastname2>
<artist2firstname2>Lewis</artist2firstname2>
<artist2lastname2>Milestone</artist2lastname2>
<description2>Film adaptation of the classic novel. Tragic and iconic tale of love and friendship told by one of Americas greatest writers.</description2>
<company2>Image Entertainment</company2>
<year2>1939</year2>
<productid2>6305081832</productid2>
<price2>9.95</price2>
</Movie2>
<Movie2>
<image href="file://images/6304039549.jpg" />
<producttype2>VHS</producttype2>
<productname2>Old Man And The Sea</productname2>
<artistfirstname2>Ernest</artistfirstname2>
<artistlastname2>Hemingway</artistlastname2>
<artist2firstname2>John</artist2firstname2>
<artist2lastname2>Sturges</artist2lastname2>
<description2>Film adaptation of the classic novel. A fish tale for the generations. A classic tale of man versus nature and his eventual defeat and triumph.</description2>
<company2>Warner Bros</company2>
<year2>1958</year2>
<productid2>6304039549</productid2>
<price2>9.95</price2>
</Movie2>
<Movie2>
<image href="file://images/B00000F17A.jpg" />
<producttype2>DVD</producttype2>
<productname2>Oliver Twist</productname2>
<artistfirstname2>Charles</artistfirstname2>
<artistlastname2>Dickens</artistlastname2>
<artist2firstname2>David</artist2firstname2>
<artist2lastname2>Lean</artist2lastname2>
<description2>Film adaptation of the classic novel. Tale of an orphan&apos;s journey from despair to triumph.</description2>
<company2>Criterion</company2>
<year2>1948</year2>
<productid2>B00000F17A</productid2>
<price2>35.99</price2>
</Movie2>
<Movie2>
<producttype2>DVD</producttype2>
<productname2>Tender Is the Night</productname2>
<artistfirstname2>F. Scott</artistfirstname2>
<artistlastname2>Fitzgerald</artistlastname2>
<artist2firstname2>Henry</artist2firstname2>
<artist2lastname2>K</artist2lastname2>
<description2>Film adaptation of the classic novel. Classic tale of wealth and tragic romance.</description2>
<company2>Unknown</company2>
<year2>1962</year2>
<productid2>B00005JORE</productid2>
<price2>9.95</price2>
</Movie2>
<Movie2>
<producttype2>DVD</producttype2>
<productname2>The Adventures of Tom Sawyer</productname2>
<artistfirstname2>Mark</artistfirstname2>
<artistlastname2>Twain</artistlastname2>
<artist2firstname2>Norman</artist2firstname2>
<artist2lastname2>Taurog</artist2lastname2>
<description2>Film adaptation of the classic novel. Classic American story of life in pre-Civil War Missouri.</description2>
<company2>Legacy Entertainment</company2>
<year2>1938</year2>
<productid2>B000LQ79W0</productid2>
<price2>9.95</price2>
</Movie2>
<Movie2>
<producttype2>DVD</producttype2>
<productname2>The Cider House Rules: A Novel</productname2>
<artistfirstname2>John</artistfirstname2>
<artistlastname2>Irving</artistlastname2>
<artist2firstname2>Lasse</artist2firstname2>
<artist2lastname2>Hallström</artist2lastname2>
<description2>Film adaptation of the classic novel. Classic tale following the life of a doctor who founded an orphanage in rural Maine before WWII and the orphans in his charge.</description2>
<company2>FilmColony</company2>
<year2>1999</year2>
<productid2>B000065K5S</productid2>
<price2>9.95</price2>
</Movie2>
<Movie2>
<image href="file://images/B0000DJZ8R.jpg" />
<producttype2>DVD</producttype2>
<productname2>The Grapes of Wrath</productname2>
<artistfirstname2>John</artistfirstname2>
<artistlastname2>Steinbeck</artistlastname2>
<artist2firstname2>John</artist2firstname2>
<artist2lastname2>Ford</artist2lastname2>
<description2>Film adaptation of the classic novel. Joad family struggle with poverty and dignity in the great Depression.</description2>
<company2>20th Century Fox</company2>
<year2>1940</year2>
<productid2>B0000DJZ8R</productid2>
<price2>9.95</price2>
</Movie2>
<Movie2>
<image href="file://images/6301247485.jpg" />
<producttype2>VHS</producttype2>
<productname2>The Great Gatsby</productname2>
<artistfirstname2>F. Scott</artistfirstname2>
<artistlastname2>Fitzgerald</artistlastname2>
<artist2firstname2>Jack</artist2firstname2>
<artist2lastname2>Clayton</artist2lastname2>
<description2>Film adaptation of the classic novel. Portrait of the excess and decadence of the Jazz Age. Fitzgerald&apos;s most popular and best selling novel.</description2>
<company2>Paramount</company2>
<year2>1974</year2>
<productid2>6301247485</productid2>
<price2>9.95</price2>
</Movie2>
<Movie2>
<image href="file://images/6304698615.jpg" />
<producttype2>DVD</producttype2>
<productname2>The Hunchback of Notre-Dame</productname2>
<artistfirstname2>Victor</artistfirstname2>
<artistlastname2>Hugo</artistlastname2>
<artist2firstname2>William</artist2firstname2>
<artist2lastname2>Dieterle</artist2lastname2>
<description2>Film adaptation of the classic novel. Rich tale of tale of love, hate, revenge, and of a deformed man, Quasimodo, in 1482 France.</description2>
<company2>RKO</company2>
<year2>1939</year2>
<productid2>6304698615</productid2>
<price2>17.99</price2>
</Movie2>
<Movie2>
<image href="file://images/B00009M9AG.jpg" />
<producttype2>DVD</producttype2>
<productname2>The Prince and the Pauper</productname2>
<artistfirstname2>Mark</artistfirstname2>
<artistlastname2>Twain</artistlastname2>
<artist2firstname2>William</artist2firstname2>
<artist2lastname2>Keighley</artist2lastname2>
<description2>Film adaptation of the classic novel. Classic tale of mistaken identity, intrigue and swashbuckling all rolled into one.</description2>
<company2>Warner Bros.</company2>
<year2>1937</year2>
<productid2>B00009M9AG</productid2>
<price2>17.99</price2>
</Movie2>
<Movie2>
<image href="file://images/B0000A0DTE.jpg" />
<producttype2>DVD</producttype2>
<productname2>The Scarlet Letter</productname2>
<artistfirstname2>Nathaniel</artistfirstname2>
<artistlastname2>Hawthorne</artistlastname2>
<artist2firstname2>Robert G.</artist2firstname2>
<artist2lastname2>Vignola</artist2lastname2>
<description2>Film adaptation of the classic novel. Guilt, repression, sin and redemption in Puritan New England before the Revolution.</description2>
<company2>Alpha Video</company2>
<year2>1934</year2>
<productid2>B0000A0DTE</productid2>
<price2>9.95</price2>
</Movie2>
<Movie2>
<image href="file://images/B000LC4ZD0.jpg" />
<producttype2>VHS</producttype2>
<productname2>The Snows of Kilimanjaro</productname2>
<artistfirstname2>Ernest</artistfirstname2>
<artistlastname2>Hemingway</artistlastname2>
<artist2firstname2>Henry</artist2firstname2>
<artist2lastname2>King</artist2lastname2>
<description2>Film adaptation of the classic short story. Life and death and adventure across Europe and Africa.</description2>
<company2>20th Century Fox</company2>
<year2>1953</year2>
<productid2>B000LC4ZD0</productid2>
<price2>9.95</price2>
</Movie2>
<Movie2>
<producttype2>DVD</producttype2>
<productname2>The World According to Garp</productname2>
<artistfirstname2>John</artistfirstname2>
<artistlastname2>Irving</artistlastname2>
<artist2firstname2>George Roy</artist2firstname2>
<artist2lastname2>Hill</artist2lastname2>
<description2>Film adaptation of the classic novel. An American tale of realistic surrealism following the life of fictional novelist T. S. Garp</description2>
<company2>Warner Bros.</company2>
<year2>1982</year2>
<productid2>B000056WRE</productid2>
<price2>10.99</price2>
</Movie2>
<Movie2>
<image href="file://images/B0000B1OGH.jpg" />
<producttype2>DVD</producttype2>
<productname2>To Have and Have Not</productname2>
<artistfirstname2>Ernest</artistfirstname2>
<artistlastname2>Hemingway</artistlastname2>
<artist2firstname2>Howard</artist2firstname2>
<artist2lastname2>Hawks</artist2lastname2>
<description2>Film adaptation of the classic novel. Adventure, danger and betrayal in pre-Civil War Cuba</description2>
<company2>Warner Bros</company2>
<year2>2003</year2>
<productid2>B0000B1OGH</productid2>
<price2>9.95</price2>
</Movie2>
<Movie2>
<image href="file://images/B00006JU7S.jpg" />
<producttype2>DVD</producttype2>
<productname2>War and Peace</productname2>
<artistfirstname2>Leo</artistfirstname2>
<artistlastname2>Tolstoy</artistlastname2>
<artist2firstname2>King</artist2firstname2>
<artist2lastname2>Vidor</artist2lastname2>
<description2>Film adaptation of the classic novel. Vast tableau of life and death in Czarist Russia during the Napoleanic Wars.</description2>
<company2>Paramount</company2>
<year2>1956</year2>
<productid2>B00006JU7S</productid2>
<price2>9.95</price2>
</Movie2>
</MV2>
